makaron
