Metadata-Version: 1.0
Name: makaron
Version: 1.0.4
Summary: Version handler
Home-page: https://gitlab.com/makaron/makaron
Author: Noel Martignoni
Author-email: noel@martignoni.fr
License: UNKNOWN
Platform: UNKNOWN
